myner/__init__.py
myner/highlight_pdf.py
myner/ner.py
myner/ner_api.py
myner/test.ipynb
myner/text_preprocessing.py
myner-0.0.6.dist-info/METADATA
myner-0.0.6.dist-info/WHEEL
myner-0.0.6.dist-info/RECORD
