Metadata-Version: 2.1
Name: myNer
Version: 0.0.6
Summary: package to execute some ner ops
Project-URL: Homepage, https://github.com/ach2ashes/Internship_nlp
Author-email: Achraf Sbai <achraf.sbai2012@gmail.com>
Classifier: Operating System :: OS Independent
Classifier: Programming Language :: Python :: 3
Requires-Python: >=3.7
